staticrab/__init__.py
staticrab/correlation.py
staticrab-0.0.3.dist-info/LICENSE
staticrab-0.0.3.dist-info/METADATA
staticrab-0.0.3.dist-info/WHEEL
staticrab-0.0.3.dist-info/top_level.txt
staticrab-0.0.3.dist-info/RECORD
