Metadata-Version: 2.1
Name: staticrab
Version: 0.0.3
Summary: Fast correlation coefficients
Home-page: https://github.com/staticrab/staticrab
Author: Vladimír Kunc
License: MIT
Platform: UNKNOWN
Classifier: License :: OSI Approved :: MIT License
Classifier: Programming Language :: Python :: 3
Classifier: Programming Language :: Python :: 3.8
Requires-Dist: numpy (>=1.16.2)
Requires-Dist: staticrab-backend (==0.0.1)
